supersockets/__init__.py
supersockets/supersockets.py
supersockets-0.1.0.dist-info/LICENSE
supersockets-0.1.0.dist-info/METADATA
supersockets-0.1.0.dist-info/WHEEL
supersockets-0.1.0.dist-info/top_level.txt
supersockets-0.1.0.dist-info/RECORD
