Metadata-Version: 2.1
Name: supersockets
Version: 0.1.0
Summary: Easy to use implementation of the built in 'socket' library
Home-page: https://github.com/JustScott/SuperSockets
Author: JustScott
Author-email: <justscottmail@protonmail.com>
License: MIT
Project-URL: Bug Reports, https://github.com/JustScott/SuperSockets/issues
Keywords: python,networking,sockets
Classifier: Development Status :: 3 - Alpha
Classifier: Environment :: Console
Classifier: Intended Audience :: Developers
Classifier: License :: OSI Approved :: MIT License
Classifier: Operating System :: OS Independent
Classifier: Programming Language :: Python :: 3.8
Classifier: Topic :: System :: Networking
License-File: LICENSE
Requires-Dist: pycryptodome (>=3.15.0)
Requires-Dist: listcrypt (>=1.0.0)
Requires-Dist: rapidrsa (>=1.0.0)
